epsilon/__init__.py
epsilon/admin.py
epsilon/apps.py
epsilon/models.py
epsilon/schema_profile.py
epsilon/signals.py
epsilon/util.py
epsilon/views.py
django_epsilon-0.8.dist-info/METADATA
django_epsilon-0.8.dist-info/WHEEL
django_epsilon-0.8.dist-info/top_level.txt
django_epsilon-0.8.dist-info/RECORD
