Metadata-Version: 2.1
Name: django-epsilon
Version: 0.8
Summary: Django Epsilon service
Home-page: UNKNOWN
Author: 
Author-email: 
License: MIT
Platform: UNKNOWN
Requires-Dist: requests
Requires-Dist: django
Requires-Dist: schema
